gmaps_tracker/__init__.py
gmaps_tracker/__main__.py
gmaps_tracker/gmaps_tracker.py
gmaps_tracker-1.0.0.dist-info/entry_points.txt
gmaps_tracker-1.0.0.dist-info/WHEEL
gmaps_tracker-1.0.0.dist-info/METADATA
gmaps_tracker-1.0.0.dist-info/RECORD
