Metadata-Version: 2.1
Name: gmaps-tracker
Version: 1.0.0
Summary: Tool for storing shared locations
Home-page: https://github.com/BercziSandor/gmaps_tracker/
License: MIT
Keywords: Google,Tracking,gmap
Author: Sandor Berczi
Author-email: Berczi.Sandor@gmail.com
Maintainer: Sandor Berczi
Maintainer-email: Berczi.Sandor@gmail.com
Requires-Python: >=3.10,<4.0
Classifier: License :: OSI Approved :: MIT License
Classifier: Programming Language :: Python :: 3
Classifier: Programming Language :: Python :: 3.10
Requires-Dist: PyYAML (>=6.0,<7.0)
Requires-Dist: geographiclib (>=2.0,<3.0)
Requires-Dist: locationsharinglib (>=4.1.8,<5.0.0)
Project-URL: Repository, https://github.com/BercziSandor/gmaps_tracker/
Project-URL: issues, https://github.com/BercziSandor/gmaps_tracker/issues
